{
  "items": [
    {
      "path": "References/UNI/MasterThesisCasperAndreas.pdf",
      "uniqueDaysOpened": 3,
      "totalTimesOpened": 18,
      "openLogs": [
        {
          "timestampMillis": 1780495216748
        },
        {
          "timestampMillis": 1780495299161
        },
        {
          "timestampMillis": 1780495775905
        },
        {
          "timestampMillis": 1780495777319
        },
        {
          "timestampMillis": 1780495892326
        },
        {
          "timestampMillis": 1780496340822
        },
        {
          "timestampMillis": 1780559335343
        },
        {
          "timestampMillis": 1780559335499
        },
        {
          "timestampMillis": 1780559341341
        },
        {
          "timestampMillis": 1780559373158
        },
        {
          "timestampMillis": 1780559479800
        },
        {
          "timestampMillis": 1780559480125
        },
        {
          "timestampMillis": 1780561785593
        },
        {
          "timestampMillis": 1780561888768
        },
        {
          "timestampMillis": 1780564552381
        },
        {
          "timestampMillis": 1780564713179
        },
        {
          "timestampMillis": 1781178207174
        },
        {
          "timestampMillis": 1781179117189
        }
      ]
    },
    {
      "path": "Inbox/2026-06-09 - Løn forhandling.md",
      "uniqueDaysOpened": 1,
      "totalTimesOpened": 2,
      "openLogs": [
        {
          "timestampMillis": 1781159869159
        },
        {
          "timestampMillis": 1781160754888
        }
      ]
    },
    {
      "path": "Inbox/ARIS AI Classification Workflow.md",
      "uniqueDaysOpened": 1,
      "totalTimesOpened": 1,
      "openLogs": [
        {
          "timestampMillis": 1781160778740
        }
      ]
    },
    {
      "path": "Archive/attachments/ARIS AI Classification Workflow - Overview.excalidraw.md",
      "uniqueDaysOpened": 1,
      "totalTimesOpened": 6,
      "openLogs": [
        {
          "timestampMillis": 1781160780264
        },
        {
          "timestampMillis": 1781162003498
        },
        {
          "timestampMillis": 1781165148606
        },
        {
          "timestampMillis": 1781165526933
        },
        {
          "timestampMillis": 1781183277491
        },
        {
          "timestampMillis": 1781183320833
        }
      ]
    },
    {
      "path": "ARIS/ARIS Config.md",
      "uniqueDaysOpened": 1,
      "totalTimesOpened": 2,
      "openLogs": [
        {
          "timestampMillis": 1781160905561
        },
        {
          "timestampMillis": 1781164353347
        }
      ]
    },
    {
      "path": "Daily/2026-06-04.md",
      "uniqueDaysOpened": 1,
      "totalTimesOpened": 1,
      "openLogs": [
        {
          "timestampMillis": 1781161377229
        }
      ]
    },
    {
      "path": "ARIS/Excalidraw/Mineral wool plastic bag - Overview.md",
      "uniqueDaysOpened": 1,
      "totalTimesOpened": 10,
      "openLogs": [
        {
          "timestampMillis": 1781161385906
        },
        {
          "timestampMillis": 1781165162327
        },
        {
          "timestampMillis": 1781165172522
        },
        {
          "timestampMillis": 1781175501105
        },
        {
          "timestampMillis": 1781176005795
        },
        {
          "timestampMillis": 1781176170437
        },
        {
          "timestampMillis": 1781176206928
        },
        {
          "timestampMillis": 1781178205238
        },
        {
          "timestampMillis": 1781178216220
        },
        {
          "timestampMillis": 1781183276858
        }
      ]
    },
    {
      "path": "ARIS/Meeting - Anders Mineral uld i plastik poser.md",
      "uniqueDaysOpened": 1,
      "totalTimesOpened": 12,
      "openLogs": [
        {
          "timestampMillis": 1781164947866
        },
        {
          "timestampMillis": 1781165151100
        },
        {
          "timestampMillis": 1781165163349
        },
        {
          "timestampMillis": 1781165526464
        },
        {
          "timestampMillis": 1781165528023
        },
        {
          "timestampMillis": 1781165894058
        },
        {
          "timestampMillis": 1781174491851
        },
        {
          "timestampMillis": 1781178551651
        },
        {
          "timestampMillis": 1781179114669
        },
        {
          "timestampMillis": 1781179119991
        },
        {
          "timestampMillis": 1781183153887
        },
        {
          "timestampMillis": 1781183157743
        }
      ]
    },
    {
      "path": "ARIS/Excalidraw/Speciale - Overview.md",
      "uniqueDaysOpened": 1,
      "totalTimesOpened": 13,
      "openLogs": [
        {
          "timestampMillis": 1781164966381
        },
        {
          "timestampMillis": 1781165150195
        },
        {
          "timestampMillis": 1781165165937
        },
        {
          "timestampMillis": 1781165476935
        },
        {
          "timestampMillis": 1781175873801
        },
        {
          "timestampMillis": 1781176168707
        },
        {
          "timestampMillis": 1781176175468
        },
        {
          "timestampMillis": 1781176677392
        },
        {
          "timestampMillis": 1781178147655
        },
        {
          "timestampMillis": 1781178205882
        },
        {
          "timestampMillis": 1781178209335
        },
        {
          "timestampMillis": 1781183155743
        },
        {
          "timestampMillis": 1781183310714
        }
      ]
    },
    {
      "path": "ARIS/Dangerous waste prompt.md",
      "uniqueDaysOpened": 1,
      "totalTimesOpened": 7,
      "openLogs": [
        {
          "timestampMillis": 1781165349977
        },
        {
          "timestampMillis": 1781165465539
        },
        {
          "timestampMillis": 1781165481737
        },
        {
          "timestampMillis": 1781176205746
        },
        {
          "timestampMillis": 1781178137757
        },
        {
          "timestampMillis": 1781178208341
        },
        {
          "timestampMillis": 1781178541641
        }
      ]
    },
    {
      "path": "Inbox/fierce-wolf.md",
      "uniqueDaysOpened": 1,
      "totalTimesOpened": 5,
      "openLogs": [
        {
          "timestampMillis": 1781165452623
        },
        {
          "timestampMillis": 1781165474631
        },
        {
          "timestampMillis": 1781165476040
        },
        {
          "timestampMillis": 1781165479042
        },
        {
          "timestampMillis": 1781165481056
        }
      ]
    },
    {
      "path": "Archive/attachments/mineral_wool_01_synth_model_report_2026-06-04.md",
      "uniqueDaysOpened": 1,
      "totalTimesOpened": 1,
      "openLogs": [
        {
          "timestampMillis": 1781183144720
        }
      ]
    },
    {
      "path": "Inbox/config.yaml.md",
      "uniqueDaysOpened": 1,
      "totalTimesOpened": 1,
      "openLogs": [
        {
          "timestampMillis": 1781183151782
        }
      ]
    }
  ]
}